setup.py
bin/tmpcleaner.py
tmpcleaner/__init__.py
tmpcleaner.egg-info/PKG-INFO
tmpcleaner.egg-info/SOURCES.txt
tmpcleaner.egg-info/dependency_links.txt
tmpcleaner.egg-info/top_level.txt
tmpcleaner/logger/__init__.py
tmpcleaner/logger/level_handler.py